mkdocs_argref_plugin/VERSION
mkdocs_argref_plugin/__init__.py
mkdocs_argref_plugin/argref.py
mkdocs_argref_plugin-0.5.0.dist-info/LICENSE
mkdocs_argref_plugin-0.5.0.dist-info/METADATA
mkdocs_argref_plugin-0.5.0.dist-info/WHEEL
mkdocs_argref_plugin-0.5.0.dist-info/entry_points.txt
mkdocs_argref_plugin-0.5.0.dist-info/top_level.txt
mkdocs_argref_plugin-0.5.0.dist-info/RECORD
