Metadata-Version: 2.1
Name: mkdocs-argref-plugin
Version: 0.5.0
Summary: MkDocs plugin to replace argumented refrences with markdown links.
Author-email: Saurabh Kumar <autolink-references-mkdocs-plugin@saurabh-kumar.com>, Richard Shadrach <rhshadrach@gmail.com>
License: MIT License
Project-URL: Documentation, https://github.com/rhshadrach/mkdocs-argref-plugin/tree/main#readme
Project-URL: Source, https://github.com/rhshadrach/mkdocs-argref-plugin
Project-URL: Tracker, https://github.com/rhshadrach/mkdocs-argref-plugin/issues
Keywords: autolinks,mkdocs,github
Classifier: Development Status :: 4 - Beta
Classifier: Programming Language :: Python
Classifier: Programming Language :: Python :: 3.8
Classifier: Programming Language :: Python :: 3.9
Classifier: Programming Language :: Python :: 3.10
Classifier: Programming Language :: Python :: 3.11
Classifier: Programming Language :: Python :: 3.12
Classifier: Intended Audience :: Developers
Classifier: Intended Audience :: System Administrators
Classifier: License :: OSI Approved :: MIT License
Classifier: Operating System :: OS Independent
Classifier: Topic :: Utilities
Requires-Python: >=3.8
License-File: LICENSE
Requires-Dist: mkdocs
Provides-Extra: dev
Requires-Dist: mkdocs-argref-plugin[lint,test]; extra == "dev"
Provides-Extra: lint
Requires-Dist: pre-commit; extra == "lint"
Provides-Extra: test
Requires-Dist: pytest; extra == "test"
